sercomm/__init__.py
sercomm/camera.py
sercomm/const.py
sercomm-0.1.1.dist-info/LICENSE.txt
sercomm-0.1.1.dist-info/METADATA
sercomm-0.1.1.dist-info/WHEEL
sercomm-0.1.1.dist-info/top_level.txt
sercomm-0.1.1.dist-info/version.txt
sercomm-0.1.1.dist-info/version_full.txt
sercomm-0.1.1.dist-info/RECORD
