Metadata-Version: 2.1
Name: sercomm
Version: 0.1.1
Summary: A Python interface for Sercomm IP camera configuration
Home-page: https://github.com/brandond/sercomm
Author: Brandon Davidson
Author-email: brad@oatmail.org
License: UNKNOWN
Platform: UNKNOWN
Classifier: Development Status :: 4 - Beta
Classifier: License :: OSI Approved :: Apache Software License
Classifier: Programming Language :: Python :: 2.7
Classifier: Programming Language :: Python :: 3.5
Classifier: Programming Language :: Python :: 3.6
Classifier: Topic :: Multimedia :: Video :: Capture
Requires-Python: >=2.7
Requires-Dist: requests
Provides-Extra: dev
Requires-Dist: setuptools-version-command ; extra == 'dev'
